{
  "name": "PartyContactMech",
  "fields": [
    {
      "fieldName": "fromDate",
      "fieldType": "LocalDate"
    },
    {
      "fieldName": "thruDate",
      "fieldType": "LocalDate"
    },
    {
      "fieldName": "nonSolicitation",
      "fieldType": "Boolean"
    }
  ],
  "relationships": [
    {
      "relationshipType": "many-to-one",
      "otherEntityName": "party",
      "otherEntityRelationshipName": "partyContactMech",
      "relationshipName": "party",
      "otherEntityField": "id"
    },
    {
      "relationshipType": "many-to-one",
      "otherEntityName": "contactMech",
      "otherEntityRelationshipName": "partyContactMech",
      "relationshipName": "contactMechanism",
      "otherEntityField": "id"
    }
  ],
  "changelogDate": "20201023032535",
  "entityTableName": "party_contact_mech",
  "dto": "no",
  "pagination": "no",
  "service": "no",
  "jpaMetamodelFiltering": false,
  "fluentMethods": true,
  "readOnly": false,
  "embedded": false,
  "clientRootFolder": "",
  "applications": "*"
}
